load_m3u8/__init__.py
load_m3u8/version.py
load_m3u8/generate/__init__.py
load_m3u8/generate/__main__.py
load_m3u8/generate/resolve.py
load_m3u8/load/__init__.py
load_m3u8/load/__main__.py
load_m3u8/load/resolve.py
load_m3u8-0.0.10.dist-info/LICENSE
load_m3u8-0.0.10.dist-info/METADATA
load_m3u8-0.0.10.dist-info/WHEEL
load_m3u8-0.0.10.dist-info/entry_points.txt
load_m3u8-0.0.10.dist-info/top_level.txt
load_m3u8-0.0.10.dist-info/RECORD
