Metadata-Version: 2.1
Name: load-m3u8
Version: 0.0.10
Summary: Download video by m3u8 file
Home-page: https://github.com/16beer/load_m3u8
Author: sunmaolin.com
Author-email: dev@sunmaolin.com
License: Apache License
Keywords: m3u8 m3u8-downloader m3u8-download
Platform: any
Classifier: Programming Language :: Python :: 3
Classifier: License :: OSI Approved :: Apache Software License
Classifier: Operating System :: OS Independent
Requires-Python: >=3.6
License-File: LICENSE
Requires-Dist: m3u8
Requires-Dist: requests
Requires-Dist: natsort
Requires-Dist: pycryptodome
Requires-Dist: ffmpy
